roboformer/__init__.py
roboformer/models/__init__.py
roboformer/models/opt/__init__.py
roboformer/models/opt/model.py
roboformer/models/opt/sampling.py
roboformer/models/opt/utils.py
roboformer/models/opt/scripts/__init__.py
roboformer/models/opt/scripts/sample.py
roboformer/scripts/__init__.py
roboformer/scripts/cli.py
roboformer/tasks/__init__.py
roboformer-0.0.1.dist-info/METADATA
roboformer-0.0.1.dist-info/WHEEL
roboformer-0.0.1.dist-info/entry_points.txt
roboformer-0.0.1.dist-info/top_level.txt
roboformer-0.0.1.dist-info/RECORD
