Metadata-Version: 2.1
Name: roboformer
Version: 0.0.1
Summary: Using toolformer for Embodied AI
Home-page: https://github.com/codekansas/roboformer
Author: Benjamin Bolte
Requires-Python: >=3.10
Requires-Dist: ml-starter
Requires-Dist: numpy
Requires-Dist: torch (>=2.0.0)
Requires-Dist: transformers
Provides-Extra: dev
Requires-Dist: black ; extra == 'dev'
Requires-Dist: cmake ; extra == 'dev'
Requires-Dist: darglint ; extra == 'dev'
Requires-Dist: mypy ; extra == 'dev'
Requires-Dist: pytest ; extra == 'dev'
Requires-Dist: ruff ; extra == 'dev'
Requires-Dist: clang-format ; extra == 'dev'
Requires-Dist: cmake-format ; extra == 'dev'
